lethean/__init__.py
lethean/api_client.py
lethean/configuration.py
lethean/exceptions.py
lethean/model_utils.py
lethean/rest.py
lethean/api/__init__.py
lethean/api/explorer_api.py
lethean/api/vpn_api.py
lethean/apis/__init__.py
lethean/model/__init__.py
lethean/model/block_dto.py
lethean/model/block_entity.py
lethean/model/block_output_entity.py
lethean/model/block_outputs_dto.py
lethean/model/block_outputs_entity.py
lethean/model/certificates_entity.py
lethean/model/ecdh_info.py
lethean/model/emission_dto.py
lethean/model/emission_entity.py
lethean/model/inputs_entity.py
lethean/model/mempool_dto.py
lethean/model/mempool_entity.py
lethean/model/mgs_entity.py
lethean/model/mixin_entity.py
lethean/model/network_stats_dto.py
lethean/model/network_stats_entity.py
lethean/model/output_entity.py
lethean/model/prove_transfer_dto.py
lethean/model/prove_transfer_entity.py
lethean/model/prove_transfer_outputs_entity.py
lethean/model/proxy_settings_entity.py
lethean/model/range_sigs_entity.py
lethean/model/raw_block_dto.py
lethean/model/raw_block_entity.py
lethean/model/raw_block_miner_tx.py
lethean/model/raw_block_miner_vin.py
lethean/model/raw_block_miner_vin_gen.py
lethean/model/raw_block_miner_vout.py
lethean/model/raw_transaction_dto.py
lethean/model/raw_transaction_entity.py
lethean/model/raw_transaction_entity_vin.py
lethean/model/raw_transaction_entity_vin_key.py
lethean/model/raw_transaction_entity_vout.py
lethean/model/raw_transaction_entity_vout_target.py
lethean/model/raw_transaction_rct_signature.py
lethean/model/rct_sig_entity.py
lethean/model/rct_sig_prunable.py
lethean/model/search_dto.py
lethean/model/search_entity.py
lethean/model/service_entity.py
lethean/model/time_range_entity.py
lethean/model/transaction_block.py
lethean/model/transaction_dto.py
lethean/model/transaction_entity.py
lethean/model/transactions_dto.py
lethean/model/transactions_entity.py
lethean/model/txn_entity.py
lethean/model/version_dto.py
lethean/model/version_entity.py
lethean-1.1.1.dist-info/METADATA
lethean-1.1.1.dist-info/WHEEL
lethean-1.1.1.dist-info/top_level.txt
lethean-1.1.1.dist-info/RECORD
