Metadata-Version: 2.1
Name: lethean
Version: 1.1.1
Summary: Lethean VPN
Home-page: https://lt.hn/en/sdk/python
Author: Lethean VPN
Author-email: contact@lethean.io
License: GPLv3
Keywords: OpenAPI,OpenAPI-Generator,Lethean VPN
Platform: UNKNOWN
Requires-Python: >=3.6
Requires-Dist: urllib3 (>=1.25.3)
Requires-Dist: python-dateutil
